Workbook

Sheet Parametros de Custo
A1: PUNK BOLOS — PARÂMETROS GLOBAIS DE CUSTOS (SENAC / SEBRAE)
A2: Preencha os valores nas células da Coluna B para calibrar automaticamente toda a formação de preços.
A4: 1. CUSTOS FIXOS MENSAIS (ESTRUTURA) | B4: VALOR (R$) | C4: OBSERVAÇÃO / REGRA SEBRAE
A5: Aluguel do Espaço | B5: 0 | C5: Deixe 0,00 se trabalhar em residência própria
A6: Energia Elétrica | B6: 160 | C6: Média mensal (forno elétrico, batedeiras, geladeiras)
A7: Gás GLP / Forno | B7: 130 | C7: Consumo médio de botijão P13 ou P45
A8: Água e Saneamento | B8: 70 | C8: Higienização constante de louças e bancadas
A9: Internet e Sistemas | B9: 90 | C9: Sistema de gestão, WhatsApp e comunicação
A10: Manutenção / Depreciação | B10: 80 | C10: Reserva mensal para conserto/reposição de equipamentos
A11: Contador ou DAS-MEI | B11: 75 | C11: Guia DAS do MEI ou honorários de contabilidade
A12: Produtos de Limpeza | B12: 60 | C12: Álcool 70%, detergentes, toucas e papel toalha
A13: Outros Custos Fixos | B13: 0 | C13: Demais despesas fixas da estrutura
A14: TOTAL DE CUSTOS FIXOS MENSAIS | B14: =SUM(B5:B13) -> 665 | C14: Soma calculada automaticamente
A16: 2. MÃO DE OBRA DIRETA (MOD) & EQUIPE | B16: VALOR | C16: DETALHAMENTO
A17: Pró-Labore do Confeiteiro | B17: 3000 | C17: Salário pretendido pelo proprietário/confeiteiro
A18: Salário de Ajudantes (Equipe) | B18: 0 | C18: Salário base bruto dos funcionários (0 se trabalhar só)
A19: Encargos Sociais CLT (%) | B19: 0.3424 | C19: 13º (8,33%) + Férias (11,11%) + FGTS (8%) + Multa (3,2%) + outros (3,6%)
A20: Provisão de Encargos Trabalhistas (R$) | B20: =IF(B18>0, B18*B19, 0) -> 0 | C20: Calculado sobre o salário dos ajudantes
A21: Benefícios Mensais (VT/VR/Cesta) | B21: 0 | C21: Valor total pago à equipe no mês
A22: TOTAL MÃO DE OBRA MENSAL | B22: =B17+B18+B20+B21 -> 3000 | C22: Salário total do confeiteiro + equipe com encargos
A24: 3. JORNADA DE TRABALHO & CAPACIDADE | B24: VALOR | C24: IMPACTO NA PRODUÇÃO
A25: Dias Trabalhados no Mês | B25: 22 | C25: 22 dias (Segunda a Sexta) ou 26 dias (Segunda a Sábado)
A26: Horas Trabalhadas por Dia | B26: 8 | C26: Jornada diária dedicada à produção
A27: Horas Produtivas no Mês | B27: =B25*B26 -> 176 | C27: Capacidade mensal de produção em horas
A28: Minutos Produtivos no Mês | B28: =B27*60 -> 10560 | C28: Capacidade mensal de produção em minutos
A30: TAXAS HORÁRIAS CALCULADAS | B30: TAXA | C30: FÓRMULA AUTOMÁTICA
A31: Custo Hora Mão de Obra (MOD) | B31: =IF(B27>0, B22/B27, 0) -> 17.05 | C31: = Total Mão de Obra / Horas Mensais
A32: Custo Minuto Mão de Obra (MOD) | B32: =IF(B28>0, B22/B28, 0) -> 0.2841 | C32: = Total Mão de Obra / Minutos Mensais
A33: Custo Hora Fixo (Estrutura) | B33: =IF(B27>0, B14/B27, 0) -> 3.78 | C33: = Total Custos Fixos / Horas Mensais
A34: Custo Minuto Fixo (Estrutura) | B34: =IF(B28>0, B14/B28, 0) -> 0.063 | C34: = Total Custos Fixos / Minutos Mensais
A36: 4. TAXAS DE VENDA, SEGURANÇA & LUCRO | B36: PERCENTUAL | C36: FINALIDADE
A37: Imposto sobre a Venda (%) | B37: 0.04 | C37: Alíquota do Simples Nacional (ou 0% para MEI)
A38: Taxa Média Maquininha (%) | B38: 0.035 | C38: Média ponderada das taxas de cartão/PIX
A39: Quebra Técnica de Insumos (%) | B39: 0.03 | C39: Margem de segurança para perdas de cocção e manipulação (3%)
A40: Margem Líquida Padrão (%) | B40: 0.25 | C40: Lucro líquido padrão desejado no caixa da empresa (25%)
A41: TOTAL DEDUÇÕES SOBRE A VENDA (%) | B41: =B37+B38 -> 0.075 | C41: Taxas retidas sobre o preço bruto de venda (7,5%)

Sheet Ficha Tecnica & Simulador
A1: FICHA TÉCNICA & SIMULADOR DE PREÇO (SENAC / SEBRAE)
A3: PARÂMETROS DO PRODUTO | B3: VALOR INFORMADO | C3: UNIDADE
A4: Nome do Produto | B4: Brigadeiro Tradicional Artesanal
A5: Tempo de Preparo / Mão de Obra | B5: 30 | C5: minutos
A6: Rendimento da Receita (Lote) | B6: 100 | C6: unidades
A7: Embalagem & Adicionais (por un) | B7: 0 | C7: R$ / un
A8: Margem Líquida Desejada (%) | B8: 0.25 | C8: % de lucro
A10: INGREDIENTE / INSUMO | B10: QTD USADA | C10: UNIDADE | D10: CUSTO DA EMBALAGEM (R$) | E10: QTD DA EMBALAGEM | F10: CUSTO NA RECEITA (R$)
A11: Leite Condensado | B11: 790 | C11: g | D11: 13.6 | E11: 790 | F11: =(B11/E11)*D11 -> 13.6
A12: Creme de Leite | B12: 400 | C12: g | D12: 5.8 | E12: 400 | F12: =(B12/E12)*D12 -> 5.8
A13: Manteiga | B13: 90 | C13: g | D13: 9.2 | E13: 200 | F13: =(B13/E13)*D13 -> 4.14
A14: Cacau em pó 100% | B14: 40 | C14: g | D14: 20 | E14: 200 | F14: =(B14/E14)*D14 -> 4
A15: Chocolate Blend Nobre | B15: 300 | C15: g | D15: 32.5 | E15: 1000 | F15: =(B15/E15)*D15 -> 9.75
A16: Forminhas simples | B16: 100 | C16: un | D16: 4 | E16: 100 | F16: =(B16/E16)*D16 -> 4
A17: Forminhas 4 pétalas | B17: 100 | C17: un | D17: 4.4 | E17: 100 | F17: =(B17/E17)*D17 -> 4.4
A18: Granulado Nobre Melken | B18: 400 | C18: g | D18: 45 | E18: 400 | F18: =(B18/E18)*D18 -> 45
A19: Caixa para 100 doces | B19: 1 | C19: un | D19: 11 | E19: 1 | F19: =(B19/E19)*D19 -> 11
A21: Subtotal Ingredientes (Custo Direto) | F21: =SUM(F11:F19) -> 101.69
A22: Insumos c/ 3% Quebra Técnica | F22: =F21*(1+'Parametros de Custo'!B39) -> 104.74
A25: DEMONSTRATIVO DE PREÇO (DRE DA RECEITA)
A26: 1. COMPOSIÇÃO DE CUSTO | B26: VALOR DO LOTE | C26: POR UNIDADE | D26: MEMÓRIA DE CÁLCULO
A27: Insumos (c/ 3% quebra técnica) | B27: =F22 -> 104.74 | C27: =B27/B6 -> 1.05 | D27: Soma dos ingredientes com quebra
A28: Mão de Obra Direta (30 min) | B28: =B5*'Parametros de Custo'!B32 -> 8.52 | C28: =B28/B6 -> 0.09 | D28: = Tempo de preparo * Custo minuto MOD
A29: Custos Fixos / Estrutura | B29: =B5*'Parametros de Custo'!B34 -> 1.89 | C29: =B29/B6 -> 0.02 | D29: = Tempo de preparo * Custo minuto Fixo
A30: Embalagem & Adicionais | B30: =B7*B6 -> 0 | C30: =B7 -> 0 | D30: Custo de embalagem unitária
A31: CUSTO UNITÁRIO TOTAL DE PRODUÇÃO | B31: =SUM(B27:B30) -> 115.15 | C31: =SUM(C27:C30) -> 1.15 | D31: Custo real de 1 unidade para sair pronta
A33: 2. PREÇO DE VENDA & LUCRO | B33: VALOR | C33: PERCENTUAL | D33: FÓRMULA / REGRA
A34: Markup Divisor | B34: =1-('Parametros de Custo'!B41+B8) -> 0.675 | D34: = 1 - (Taxas de Venda + Margem Desejada)
A35: PREÇO SUGERIDO (CARDÁPIO) | B35: =C31/B34 -> 1.71 | C35: por unidade | D35: = Custo Unitário Total / Markup Divisor
A36: LUCRO LÍQUIDO NO CAIXA | B36: =B35-C31-(B35*'Parametros de Custo'!B41) -> 0.43 | C36: =B36/B35 -> 0.25 | D36: Dinheiro limpo no caixa da empresa por unidade
A38: 3. METAS & DESEMPENHO ESTRATÉGICO | B38: VALOR | C38: PERCENTUAL | D38: IMPACTO ESTRATÉGICO
A39: Margem de Contribuição Unitária | B39: =B35-(C27+C30)-(B35*'Parametros de Custo'!B41) -> 0.53 | C39: =B39/B35 -> 0.31 | D39: = Preço - CMV - Taxas (o que sobra para pagar as despesas fixas)
A40: Meta Ponto de Equilíbrio Mensal | B40: =CEILING(('Parametros de Custo'!B14+'Parametros de Custo'!B22)/B39, 1) -> 6916 | C40: unidades / mês | D40: Quantidade necessária para quitar todas as despesas e salário
A41: Meta Ponto de Equilíbrio Diária | B41: =CEILING(B40/'Parametros de Custo'!B25, 1) -> 315 | C41: unidades / dia útil | D41: Meta diária de produção/vendas

Sheet Ponto de Equilibrio & Metas
A1: PONTO DE EQUILÍBRIO & METAS DE FATURAMENTO OPERACIONAL
A3: ESTRUTURA GERAL DE GASTOS FIXOS | B3: VALOR MENSAL (R$) | C3: ORIGEM DOS DADOS
A4: Total de Custos Fixos (Estrutura) | B4: ='Parametros de Custo'!B14 -> 665 | C4: Aluguel, Luz, Gás, Água, Internet, Contador...
A5: Total de Mão de Obra (Pró-Labore + Equipe) | B5: ='Parametros de Custo'!B22 -> 3000 | C5: Salário do Confeiteiro + Ajudantes + Encargos
A6: META DE COBERTURA MENSAL | B6: =B4+B5 -> 3665 | C6: Total necessário para zerar todas as contas da empresa
A8: COMO FUNCIONA O PONTO DE EQUILÍBRIO?
A9: 1. Antes de atingir a meta: | B9: Pagar as contas | C9: Cada venda gera Margem de Contribuição para pagar os R$ 3.665 fixos.
A10: 2. Ao atingir a meta (100%): | B10: Ponto de Equilíbrio | C10: Todas as despesas da empresa e o seu salário estão 100% pagos!
A11: 3. Acima da meta (Vendas extras): | B11: Lucro & Investimento | C11: Cada venda extra vira Lucro Líquido Real para reinvestir ou retirar lucros.
